sicdeploy/__init__.py
sicdeploy/run.py
sicdeploy/commands/build.py
sicdeploy/commands/config.py
sicdeploy/templates/meta.yaml.dist
sicdeploy/templates/setup.py.dist
sicdeploy-0.2.1.dist-info/METADATA
sicdeploy-0.2.1.dist-info/WHEEL
sicdeploy-0.2.1.dist-info/entry_points.txt
sicdeploy-0.2.1.dist-info/top_level.txt
sicdeploy-0.2.1.dist-info/RECORD
