Metadata-Version: 2.1
Name: sicdeploy
Version: 0.2.1
License: LICENSE
Requires-Dist: impose-cli
Requires-Dist: twine
Requires-Dist: awscli
Requires-Dist: PyYAML
Requires-Dist: wheel
